uncolor
