Metadata-Version: 2.1
Name: colorizing-tool-uncolor
Version: 1.0.1
Summary: 🎨 | Uncomplicated colorizing tool
Home-page: https://github.com/gatomo-oficial/uncolor
Download-URL: https://github.com/gatomo-oficial/uncolor/archive/refs/tags/1.0.tar.gz
Author: Gátomo
Author-email: dontSendMeAnEmail@thanks.com
License: UNKNOWN
Keywords: Terminals,Color,Colorize,Uncolor,Styling
Platform: UNKNOWN
License-File: LICENSE
